contact_energy_nz/__init__.py
contact_energy_nz/consts.py
contact_energy_nz/contact_energy_api.py
contact_energy_nz/usage_datum.py
contact_energy_nz-0.1.8595366105.dist-info/LICENSE
contact_energy_nz-0.1.8595366105.dist-info/METADATA
contact_energy_nz-0.1.8595366105.dist-info/WHEEL
contact_energy_nz-0.1.8595366105.dist-info/top_level.txt
contact_energy_nz-0.1.8595366105.dist-info/RECORD
