Metadata-Version: 2.1
Name: contact-energy-nz
Version: 0.1.8595366105
Summary: API Connector to fetch usage data from Contact Energy NZ utilities provider
Author-email: Tkhadimullin <hello@wiseowls.co.nz>
License: MIT
Project-URL: Homepage, https://github.com/tkhadimullin/contact-energy-nz
Project-URL: Bug Tracker, https://github.com/tkhadimullin/contact-energy-nz/issues
License-File: LICENSE
